adaptive_rtl/systolic_pe.sv
`timescale 1ns/1ps

module systolic_pe #(
    parameter int DATA_WIDTH = 8,
    parameter int ACC_WIDTH  = 32
)(
    input logic clk,
    input logic rst_n,
    input logic clear,

    input logic signed [DATA_WIDTH-1:0] a_in,
    input logic signed [DATA_WIDTH-1:0] b_in,

    input logic a_valid_in,
    input logic b_valid_in,

    output logic signed [DATA_WIDTH-1:0] a_out,
    output logic signed [DATA_WIDTH-1:0] b_out,

    output logic a_valid_out,
    output logic b_valid_out,

    output logic signed [ACC_WIDTH-1:0] acc_out
);

    localparam int PRODUCT_WIDTH = 2 * DATA_WIDTH;

    logic signed [DATA_WIDTH-1:0] a_reg;
    logic signed [DATA_WIDTH-1:0] b_reg;

    logic signed [PRODUCT_WIDTH-1:0] product_reg;
    logic signed [ACC_WIDTH-1:0] accumulator;

    logic a_valid_reg;
    logic b_valid_reg;
    logic product_valid_reg;

    always_ff @(posedge clk) begin

        if (!rst_n) begin

            a_reg             <= '0;
            b_reg             <= '0;
            product_reg       <= '0;
            accumulator       <= '0;

            a_valid_reg       <= 1'b0;
            b_valid_reg       <= 1'b0;
            product_valid_reg <= 1'b0;

        end
        else if (clear) begin

            a_reg             <= '0;
            b_reg             <= '0;
            product_reg       <= '0;
            accumulator       <= '0;

            a_valid_reg       <= 1'b0;
            b_valid_reg       <= 1'b0;
            product_valid_reg <= 1'b0;

        end
        else begin

            // Pipeline stage 1:
            // Capture and forward A/B.
            a_reg <= a_in;
            b_reg <= b_in;

            a_valid_reg <= a_valid_in;
            b_valid_reg <= b_valid_in;

            // Pipeline stage 2:
            // Signed multiplication.
            product_reg <=
                $signed(a_reg) * $signed(b_reg);

            product_valid_reg <=
                a_valid_reg && b_valid_reg;

            // Pipeline stage 3:
            // Output-stationary accumulation.
            if (product_valid_reg)
                accumulator <=
                    accumulator + $signed(product_reg);

        end

    end

    assign a_out = a_reg;
    assign b_out = b_reg;

    assign a_valid_out = a_valid_reg;
    assign b_valid_out = b_valid_reg;

    assign acc_out = accumulator;

endmodule

adaptive_sim/pe_tb.sv
`timescale 1ns/1ps

module pe_tb;

    logic clk;
    logic rst_n;
    logic clear;

    // ------------------------------------------------------------
    // INT8 PE signals
    // ------------------------------------------------------------
    logic signed [7:0]  a8, b8;
    logic               a8_valid, b8_valid;
    logic signed [7:0]  a8_out, b8_out;
    logic               a8_valid_out, b8_valid_out;
    logic signed [31:0] acc8;

    // ------------------------------------------------------------
    // INT16 PE signals
    // ------------------------------------------------------------
    logic signed [15:0] a16, b16;
    logic               a16_valid, b16_valid;
    logic signed [15:0] a16_out, b16_out;
    logic               a16_valid_out, b16_valid_out;
    logic signed [47:0] acc16;

    // ------------------------------------------------------------
    // INT32 PE signals
    // ------------------------------------------------------------
    logic signed [31:0] a32, b32;
    logic               a32_valid, b32_valid;
    logic signed [31:0] a32_out, b32_out;
    logic               a32_valid_out, b32_valid_out;
    logic signed [64:0] acc32;

    // ============================================================
    // DUT 1 : INT8
    // ============================================================

    systolic_pe #(
        .DATA_WIDTH(8),
        .ACC_WIDTH(32)
    ) pe_int8 (
        .clk(clk),
        .rst_n(rst_n),
        .clear(clear),

        .a_in(a8),
        .b_in(b8),
        .a_valid_in(a8_valid),
        .b_valid_in(b8_valid),

        .a_out(a8_out),
        .b_out(b8_out),
        .a_valid_out(a8_valid_out),
        .b_valid_out(b8_valid_out),

        .acc_out(acc8)
    );

    // ============================================================
    // DUT 2 : INT16
    // ============================================================

    systolic_pe #(
        .DATA_WIDTH(16),
        .ACC_WIDTH(48)
    ) pe_int16 (
        .clk(clk),
        .rst_n(rst_n),
        .clear(clear),

        .a_in(a16),
        .b_in(b16),
        .a_valid_in(a16_valid),
        .b_valid_in(b16_valid),

        .a_out(a16_out),
        .b_out(b16_out),
        .a_valid_out(a16_valid_out),
        .b_valid_out(b16_valid_out),

        .acc_out(acc16)
    );

    // ============================================================
    // DUT 3 : INT32
    // ============================================================

    systolic_pe #(
        .DATA_WIDTH(32),
        .ACC_WIDTH(65)
    ) pe_int32 (
        .clk(clk),
        .rst_n(rst_n),
        .clear(clear),

        .a_in(a32),
        .b_in(b32),
        .a_valid_in(a32_valid),
        .b_valid_in(b32_valid),

        .a_out(a32_out),
        .b_out(b32_out),
        .a_valid_out(a32_valid_out),
        .b_valid_out(b32_valid_out),

        .acc_out(acc32)
    );


    // ============================================================
    // 100 MHz clock
    // ============================================================

    initial begin
        clk = 1'b0;
        forever #5 clk = ~clk;
    end


    // ============================================================
    // Drive all three PEs at once
    // ============================================================

    task automatic drive_inputs(
        input integer signed a8_value,
        input integer signed b8_value,

        input integer signed a16_value,
        input integer signed b16_value,

        input longint signed a32_value,
        input longint signed b32_value,

        input logic valid
    );
        begin
            @(negedge clk);

            a8  = a8_value;
            b8  = b8_value;

            a16 = a16_value;
            b16 = b16_value;

            a32 = a32_value;
            b32 = b32_value;

            a8_valid  = valid;
            b8_valid  = valid;

            a16_valid = valid;
            b16_valid = valid;

            a32_valid = valid;
            b32_valid = valid;
        end
    endtask


    // ============================================================
    // Clear all PEs
    // ============================================================

    task automatic clear_pes;
        begin
            @(negedge clk);
            clear = 1'b1;

            @(negedge clk);
            clear = 1'b0;

            #1;
        end
    endtask


    // ============================================================
    // Test sequence
    // ============================================================

    initial begin

        // Optional waveform output
        $dumpfile("pe_param.vcd");
        $dumpvars(0, pe_tb);

        // Defaults
        rst_n = 1'b0;
        clear = 1'b0;

        a8 = '0;
        b8 = '0;
        a16 = '0;
        b16 = '0;
        a32 = '0;
        b32 = '0;

        a8_valid  = 1'b0;
        b8_valid  = 1'b0;
        a16_valid = 1'b0;
        b16_valid = 1'b0;
        a32_valid = 1'b0;
        b32_valid = 1'b0;


        // ========================================================
        // RESET
        // ========================================================

        repeat (3) @(posedge clk);

        @(negedge clk);
        rst_n = 1'b1;


        // ========================================================
        // TEST 1
        //
        // Same arithmetic on every precision.
        //
        // 2*5 + 3*2 + (-1)*6 + 4*3
        //
        // = 10 + 6 - 6 + 12
        // = 22
        // ========================================================

        $display("");
        $display("==========================================");
        $display("TEST 1: COMMON ARITHMETIC TEST");
        $display("==========================================");

        drive_inputs( 2, 5,   2, 5,   2, 5, 1'b1);
        drive_inputs( 3, 2,   3, 2,   3, 2, 1'b1);
        drive_inputs(-1, 6,  -1, 6,  -1, 6, 1'b1);
        drive_inputs( 4, 3,   4, 3,   4, 3, 1'b1);

        // Drain the 3-stage PE pipeline
        drive_inputs(0, 0, 0, 0, 0, 0, 1'b0);
        drive_inputs(0, 0, 0, 0, 0, 0, 1'b0);

        repeat (2) @(posedge clk);
        #1;

        if (acc8 !== 32'sd22)
            $fatal(1, "INT8 FAILED: expected 22, got %0d",
                   $signed(acc8));

        if (acc16 !== 48'sd22)
            $fatal(1, "INT16 FAILED: expected 22, got %0d",
                   $signed(acc16));

        if (acc32 !== 65'sd22)
            $fatal(1, "INT32 FAILED: expected 22, got %0d",
                   $signed(acc32));

        $display("INT8  PE PASS : %0d", $signed(acc8));
        $display("INT16 PE PASS : %0d", $signed(acc16));
        $display("INT32 PE PASS : %0d", $signed(acc32));


        // ========================================================
        // CLEAR
        // ========================================================

        clear_pes();

        if (acc8 !== 0 || acc16 !== 0 || acc32 !== 0)
            $fatal(1, "CLEAR TEST FAILED");

        $display("");
        $display("CLEAR TEST PASS");


        // ========================================================
        // TEST 2
        //
        // Precision-specific values.
        //
        // These prove that the wider PEs genuinely support values
        // unavailable to the narrower PEs.
        // ========================================================

        $display("");
        $display("==========================================");
        $display("TEST 2: WIDTH-SPECIFIC ARITHMETIC");
        $display("==========================================");

        /*
         * INT8:
         *
         * 100*2 + (-50)*3
         * = 200 - 150
         * = 50
         *
         *
         * INT16:
         *
         * 1000*20 + (-300)*4
         * = 20000 - 1200
         * = 18800
         *
         *
         * INT32:
         *
         * 70000*70000 + (-100000)*10000
         *
         * = 4,900,000,000
         * - 1,000,000,000
         *
         * = 3,900,000,000
         */

        drive_inputs(
             100,      2,
            1000,     20,
           70000,  70000,
            1'b1
        );

        drive_inputs(
             -50,      3,
            -300,      4,
         -100000,  10000,
            1'b1
        );

        drive_inputs(0, 0, 0, 0, 0, 0, 1'b0);
        drive_inputs(0, 0, 0, 0, 0, 0, 1'b0);

        repeat (2) @(posedge clk);
        #1;


        // INT8 expected = 50
        if ($signed(acc8) !== 32'sd50)
            $fatal(1,
                "INT8 WIDTH TEST FAILED: expected 50, got %0d",
                $signed(acc8)
            );


        // INT16 expected = 18800
        if ($signed(acc16) !== 48'sd18800)
            $fatal(1,
                "INT16 WIDTH TEST FAILED: expected 18800, got %0d",
                $signed(acc16)
            );


        // INT32 expected = 3,900,000,000
        if ($signed(acc32) !== 65'sd3900000000)
            $fatal(1,
                "INT32 WIDTH TEST FAILED: expected 3900000000, got %0d",
                $signed(acc32)
            );


        $display(
            "INT8  WIDTH TEST PASS : %0d",
            $signed(acc8)
        );

        $display(
            "INT16 WIDTH TEST PASS : %0d",
            $signed(acc16)
        );

        $display(
            "INT32 WIDTH TEST PASS : %0d",
            $signed(acc32)
        );


        // ========================================================

        $display("");
        $display("==========================================");
        $display("ALL PARAMETERIZED PE TESTS PASSED");
        $display("==========================================");
        $display("");

        $finish;

    end

endmodule

pe_param.vcd
$date
	Mon Sep 21 19:29:20 2026
$end
$version
	Icarus Verilog
$end
$timescale
	1ps
$end
$scope module pe_tb $end
$var wire 1 ! b8_valid_out $end
$var wire 8 " b8_out [7:0] $end
$var wire 1 # b32_valid_out $end
$var wire 32 $ b32_out [31:0] $end
$var wire 1 % b16_valid_out $end
$var wire 16 & b16_out [15:0] $end
$var wire 32 ' acc8 [31:0] $end
$var wire 65 ( acc32 [64:0] $end
$var wire 48 ) acc16 [47:0] $end
$var wire 1 * a8_valid_out $end
$var wire 8 + a8_out [7:0] $end
$var wire 1 , a32_valid_out $end
$var wire 32 - a32_out [31:0] $end
$var wire 1 . a16_valid_out $end
$var wire 16 / a16_out [15:0] $end
$var reg 16 0 a16 [15:0] $end
$var reg 1 1 a16_valid $end
$var reg 32 2 a32 [31:0] $end
$var reg 1 3 a32_valid $end
$var reg 8 4 a8 [7:0] $end
$var reg 1 5 a8_valid $end
$var reg 16 6 b16 [15:0] $end
$var reg 1 7 b16_valid $end
$var reg 32 8 b32 [31:0] $end
$var reg 1 9 b32_valid $end
$var reg 8 : b8 [7:0] $end
$var reg 1 ; b8_valid $end
$var reg 1 < clear $end
$var reg 1 = clk $end
$var reg 1 > rst_n $end
$scope module pe_int16 $end
$var wire 16 ? a_in [15:0] $end
$var wire 16 @ a_out [15:0] $end
$var wire 1 1 a_valid_in $end
$var wire 1 . a_valid_out $end
$var wire 48 A acc_out [47:0] $end
$var wire 16 B b_in [15:0] $end
$var wire 16 C b_out [15:0] $end
$var wire 1 7 b_valid_in $end
$var wire 1 % b_valid_out $end
$var wire 1 < clear $end
$var wire 1 = clk $end
$var wire 1 > rst_n $end
$var parameter 32 D ACC_WIDTH $end
$var parameter 32 E DATA_WIDTH $end
$var parameter 32 F PRODUCT_WIDTH $end
$var reg 16 G a_reg [15:0] $end
$var reg 1 H a_valid_reg $end
$var reg 48 I accumulator [47:0] $end
$var reg 16 J b_reg [15:0] $end
$var reg 1 K b_valid_reg $end
$var reg 32 L product_reg [31:0] $end
$var reg 1 M product_valid_reg $end
$upscope $end
$scope module pe_int32 $end
$var wire 32 N a_in [31:0] $end
$var wire 32 O a_out [31:0] $end
$var wire 1 3 a_valid_in $end
$var wire 1 , a_valid_out $end
$var wire 65 P acc_out [64:0] $end
$var wire 32 Q b_in [31:0] $end
$var wire 32 R b_out [31:0] $end
$var wire 1 9 b_valid_in $end
$var wire 1 # b_valid_out $end
$var wire 1 < clear $end
$var wire 1 = clk $end
$var wire 1 > rst_n $end
$var parameter 32 S ACC_WIDTH $end
$var parameter 32 T DATA_WIDTH $end
$var parameter 32 U PRODUCT_WIDTH $end
$var reg 32 V a_reg [31:0] $end
$var reg 1 W a_valid_reg $end
$var reg 65 X accumulator [64:0] $end
$var reg 32 Y b_reg [31:0] $end
$var reg 1 Z b_valid_reg $end
$var reg 64 [ product_reg [63:0] $end
$var reg 1 \ product_valid_reg $end
$upscope $end
$scope module pe_int8 $end
$var wire 8 ] a_in [7:0] $end
$var wire 8 ^ a_out [7:0] $end
$var wire 1 5 a_valid_in $end
$var wire 1 * a_valid_out $end
$var wire 32 _ acc_out [31:0] $end
$var wire 8 ` b_in [7:0] $end
$var wire 8 a b_out [7:0] $end
$var wire 1 ; b_valid_in $end
$var wire 1 ! b_valid_out $end
$var wire 1 < clear $end
$var wire 1 = clk $end
$var wire 1 > rst_n $end
$var parameter 32 b ACC_WIDTH $end
$var parameter 32 c DATA_WIDTH $end
$var parameter 32 d PRODUCT_WIDTH $end
$var reg 8 e a_reg [7:0] $end
$var reg 1 f a_valid_reg $end
$var reg 32 g accumulator [31:0] $end
$var reg 8 h b_reg [7:0] $end
$var reg 1 i b_valid_reg $end
$var reg 16 j product_reg [15:0] $end
$var reg 1 k product_valid_reg $end
$upscope $end
$scope task clear_pes $end
$upscope $end
$scope task drive_inputs $end
$upscope $end
$upscope $end
$enddefinitions $end
$comment Show the parameter values. $end
$dumpall
b10000 d
b1000 c
b100000 b
b1000000 U
b100000 T
b1000001 S
b100000 F
b10000 E
b110000 D
$end
#0
$dumpvars
xk
bx j
xi
bx h
bx g
xf
bx e
bx a
b0 `
bx _
bx ^
b0 ]
x\
bx [
xZ
bx Y
bx X
xW
bx V
bx R
b0 Q
bx P
bx O
b0 N
xM
bx L
xK
bx J
bx I
xH
bx G
bx C
b0 B
bx A
bx @
b0 ?
0>
0=
0<
0;
b0 :
09
b0 8
07
b0 6
05
b0 4
03
b0 2
01
b0 0
bx /
x.
bx -
x,
bx +
x*
bx )
bx (
bx '
bx &
x%
bx $
x#
bx "
x!
$end
#5000
0k
0!
0i
0*
0f
b0 '
b0 _
b0 g
b0 j
b0 "
b0 a
b0 h
b0 +
b0 ^
b0 e
0M
0%
0K
0.
0H
b0 )
b0 A
b0 I
b0 L
b0 &
b0 C
b0 J
b0 /
b0 @
b0 G
0\
0#
0Z
0,
0W
b0 (
b0 P
b0 X
b0 [
b0 $
b0 R
b0 Y
b0 -
b0 O
b0 V
1=
#10000
0=
#15000
1=
#20000
0=
#25000
1=
#30000
1>
0=
#35000
1=
#40000
19
13
17
11
1;
15
b101 8
b101 Q
b10 2
b10 N
b101 6
b101 B
b10 0
b10 ?
b101 :
b101 `
b10 4
b10 ]
0=
#45000
1!
1i
1*
1f
b101 "
b101 a
b101 h
b10 +
b10 ^
b10 e
1%
1K
1.
1H
b101 &
b101 C
b101 J
b10 /
b10 @
b10 G
1#
1Z
1,
1W
b101 $
b101 R
b101 Y
b10 -
b10 O
b10 V
1=
#50000
b10 8
b10 Q
b11 2
b11 N
b10 6
b10 B
b11 0
b11 ?
b10 :
b10 `
b11 4
b11 ]
0=
#55000
1\
b1010 [
b10 $
b10 R
b10 Y
b11 -
b11 O
b11 V
1M
b1010 L
b10 &
b10 C
b10 J
b11 /
b11 @
b11 G
1k
b1010 j
b10 "
b10 a
b10 h
b11 +
b11 ^
b11 e
1=
#60000
b110 8
b110 Q
b11111111111111111111111111111111 2
b11111111111111111111111111111111 N
b110 6
b110 B
b1111111111111111 0
b1111111111111111 ?
b110 :
b110 `
b11111111 4
b11111111 ]
0=
#65000
b1010 '
b1010 _
b1010 g
b110 j
b110 "
b110 a
b110 h
b11111111 +
b11111111 ^
b11111111 e
b1010 )
b1010 A
b1010 I
b110 L
b110 &
b110 C
b110 J
b1111111111111111 /
b1111111111111111 @
b1111111111111111 G
b1010 (
b1010 P
b1010 X
b110 [
b110 $
b110 R
b110 Y
b11111111111111111111111111111111 -
b11111111111111111111111111111111 O
b11111111111111111111111111111111 V
1=
#70000
b11 8
b11 Q
b100 2
b100 N
b11 6
b11 B
b100 0
b100 ?
b11 :
b11 `
b100 4
b100 ]
0=
#75000
b10000 (
b10000 P
b10000 X
b1111111111111111111111111111111111111111111111111111111111111010 [
b11 $
b11 R
b11 Y
b100 -
b100 O
b100 V
b10000 )
b10000 A
b10000 I
b11111111111111111111111111111010 L
b11 &
b11 C
b11 J
b100 /
b100 @
b100 G
b10000 '
b10000 _
b10000 g
b1111111111111010 j
b11 "
b11 a
b11 h
b100 +
b100 ^
b100 e
1=
#80000
09
03
07
01
0;
05
b0 8
b0 Q
b0 2
b0 N
b0 6
b0 B
b0 0
b0 ?
b0 :
b0 `
b0 4
b0 ]
0=
#85000
b1010 '
b1010 _
b1010 g
b1100 j
0!
0i
0*
0f
b0 "
b0 a
b0 h
b0 +
b0 ^
b0 e
b1010 )
b1010 A
b1010 I
b1100 L
0%
0K
0.
0H
b0 &
b0 C
b0 J
b0 /
b0 @
b0 G
b1010 (
b1010 P
b1010 X
b1100 [
0#
0Z
0,
0W
b0 $
b0 R
b0 Y
b0 -
b0 O
b0 V
1=
#90000
0=
#95000
b10110 (
b10110 P
b10110 X
0\
b0 [
b10110 )
b10110 A
b10110 I
0M
b0 L
b10110 '
b10110 _
b10110 g
0k
b0 j
1=
#100000
0=
#105000
1=
#110000
1<
0=
#115000
b0 (
b0 P
b0 X
b0 )
b0 A
b0 I
b0 '
b0 _
b0 g
1=
#120000
0<
0=
#125000
1=
#130000
19
13
17
11
1;
15
b10001000101110000 8
b10001000101110000 Q
b10001000101110000 2
b10001000101110000 N
b10100 6
b10100 B
b1111101000 0
b1111101000 ?
b10 :
b10 `
b1100100 4
b1100100 ]
0=
#135000
1#
1Z
1,
1W
b10001000101110000 $
b10001000101110000 R
b10001000101110000 Y
b10001000101110000 -
b10001000101110000 O
b10001000101110000 V
1%
1K
1.
1H
b10100 &
b10100 C
b10100 J
b1111101000 /
b1111101000 @
b1111101000 G
1!
1i
1*
1f
b10 "
b10 a
b10 h
b1100100 +
b1100100 ^
b1100100 e
1=
#140000
b10011100010000 8
b10011100010000 Q
b11111111111111100111100101100000 2
b11111111111111100111100101100000 N
b100 6
b100 B
b1111111011010100 0
b1111111011010100 ?
b11 :
b11 `
b11001110 4
b11001110 ]
0=
#145000
1k
b11001000 j
b11 "
b11 a
b11 h
b11001110 +
b11001110 ^
b11001110 e
1M
b100111000100000 L
b100 &
b100 C
b100 J
b1111111011010100 /
b1111111011010100 @
b1111111011010100 G
1\
b100100100000100000001000100000000 [
b10011100010000 $
b10011100010000 R
b10011100010000 Y
b11111111111111100111100101100000 -
b11111111111111100111100101100000 O
b11111111111111100111100101100000 V
1=
#150000
09
03
07
01
0;
05
b0 8
b0 Q
b0 2
b0 N
b0 6
b0 B
b0 0
b0 ?
b0 :
b0 `
b0 4
b0 ]
0=
#155000
b100100100000100000001000100000000 (
b100100100000100000001000100000000 P
b100100100000100000001000100000000 X
b1111111111111111111111111111111111000100011001010011011000000000 [
0#
0Z
0,
0W
b0 $
b0 R
b0 Y
b0 -
b0 O
b0 V
b100111000100000 )
b100111000100000 A
b100111000100000 I
b11111111111111111111101101010000 L
0%
0K
0.
0H
b0 &
b0 C
b0 J
b0 /
b0 @
b0 G
b11001000 '
b11001000 _
b11001000 g
b1111111101101010 j
0!
0i
0*
0f
b0 "
b0 a
b0 h
b0 +
b0 ^
b0 e
1=
#160000
0=
#165000
b110010 '
b110010 _
b110010 g
0k
b0 j
b100100101110000 )
b100100101110000 A
b100100101110000 I
0M
b0 L
b11101000011101010100011100000000 (
b11101000011101010100011100000000 P
b11101000011101010100011100000000 X
0\
b0 [
1=
